{
  "produtos": [
    {
      "id": 1,
      "nome": "Hamburguer",
      "preco": 10
    },
    {
      "id": 2,
      "nome": "Refrigerante em lata",
      "preco": 7
    },
    {
      "id": 3,
      "nome": "Salada de frutas",
      "preco": 3.5
    },
    {
      "nome": "Mousse de chocolate",
      "preco": 5,
      "id": 4
    },
    {
      "nome": "Sorvete de baunilha",
      "preco": 3,
      "id": 5
    },
    {
      "nome": "Misto quente",
      "preco": 12,
      "id": 6
    }
  ]
}